.gitignore
CHANGELOG.md
LICENSE.txt
MANIFEST.in
README.md
requirements.txt
setup.cfg
setup.py
docs/examples/PIPELINE.md
docs/examples/TRANSFORMER.md
docs/images/gplv3-88x31.png
docs/images/transformer_output.png
src/tamag/__init__.py
src/tamag.egg-info/PKG-INFO
src/tamag.egg-info/SOURCES.txt
src/tamag.egg-info/dependency_links.txt
src/tamag.egg-info/not-zip-safe
src/tamag.egg-info/requires.txt
src/tamag.egg-info/top_level.txt
src/tamag/datasets/__init__.py
src/tamag/datasets/_load_fits_from_path.py
src/tamag/datasets/_load_fits_sample.py
src/tamag/datasets/fulldisk_samples/hmi.sharp_fulldisk_sample_1_TAI.magnetogram.fits
src/tamag/datasets/fulldisk_samples/hmi.sharp_fulldisk_sample_2_TAI.magnetogram.fits
src/tamag/datasets/fulldisk_samples/hmi.sharp_fulldisk_sample_3_TAI.magnetogram.fits
src/tamag/datasets/patch_samples/__init__.py
src/tamag/datasets/patch_samples/hmi.sharp_patch_sample_1_TAI.bitmap.fits
src/tamag/datasets/patch_samples/hmi.sharp_patch_sample_1_TAI.magnetogram.fits
src/tamag/datasets/patch_samples/hmi.sharp_patch_sample_2_TAI.bitmap.fits
src/tamag/datasets/patch_samples/hmi.sharp_patch_sample_2_TAI.magnetogram.fits
src/tamag/datasets/patch_samples/hmi.sharp_patch_sample_3_TAI.bitmap.fits
src/tamag/datasets/patch_samples/hmi.sharp_patch_sample_3_TAI.magnetogram.fits
src/tamag/pipeline/__init__.py
src/tamag/pipeline/_pipeline.py
src/tamag/pipeline/tests/__init__.py
src/tamag/pipeline/tests/test_pipeline.py
src/tamag/transforms/__init__.py
src/tamag/transforms/_bitmap_cropping_transformer.py
src/tamag/transforms/_byte_scaling_transformer.py
src/tamag/transforms/_denoise_transformer.py
src/tamag/transforms/_flip_transformer.py
src/tamag/transforms/_gaussian_blur_transformer.py
src/tamag/transforms/_histogram_equalizer_transformer.py
src/tamag/transforms/_informative_patch_transformer.py
src/tamag/transforms/_invert_polarity_transformer.py
src/tamag/transforms/_pad_transformer.py
src/tamag/transforms/_random_noise_transformer.py
src/tamag/transforms/_resize_by_half_transformer.py
src/tamag/transforms/_rotation_transformer.py
src/tamag/transforms/tests/__init__.py
src/tamag/transforms/tests/test_bitmap_cropping_transformer.py
