Metadata-Version: 2.1
Name: tamag
Version: 1.0.0
Summary: "Magnetogram Transformations: A Python Toolkit for Transforming and Enhancing Magnetogram fits"
Home-page: https://github.com/Adeyeha/tamag
Author: Temitope Adeyeha
Author-email: tadeyeha1@student.gsu.edu
License: GPL-3.0-or-later
Project-URL: Documentation, https://github.com/Adeyeha/tamag/blob/master/docs/examples/TRANSFORMER.md
Project-URL: Source Code, https://github.com/Adeyeha/tamag
Project-URL: Bug Tracker, https://github.com/Adeyeha/tamag/issues
Project-URL: Pull Request, https://github.com/Adeyeha/tamag/pulls
Keywords: solar,space weather,mvts,imbalance,sampling,features,augmentation,magnetogram,bitmap,fits
Platform: any
Classifier: Development Status :: 4 - Beta
Classifier: Intended Audience :: Science/Research
Classifier: License :: OSI Approved :: GNU General Public License v3 (GPLv3)
Classifier: Natural Language :: English
Classifier: Operating System :: OS Independent
Classifier: Programming Language :: Python :: 3
Classifier: Topic :: Scientific/Engineering :: Information Analysis
Provides: tamag
Requires-Python: >=3.9
License-File: LICENSE.txt
